miu_core/__init__.py
miu_core/modes.py
miu_core/paths.py
miu_core/usage.py
miu_core/version.py
miu_core/agents/__init__.py
miu_core/agents/base.py
miu_core/agents/react.py
miu_core/commands/__init__.py
miu_core/commands/executor.py
miu_core/commands/registry.py
miu_core/commands/schema.py
miu_core/hooks/__init__.py
miu_core/hooks/events.py
miu_core/hooks/executor.py
miu_core/hooks/registry.py
miu_core/logging/__init__.py
miu_core/logging/session_logger.py
miu_core/logging/types.py
miu_core/mcp/__init__.py
miu_core/mcp/client.py
miu_core/mcp/protocol.py
miu_core/mcp/stdio.py
miu_core/memory/__init__.py
miu_core/memory/base.py
miu_core/memory/short_term.py
miu_core/memory/truncation.py
miu_core/models/__init__.py
miu_core/models/messages.py
miu_core/patterns/__init__.py
miu_core/patterns/orchestrator.py
miu_core/patterns/pipeline.py
miu_core/patterns/routing.py
miu_core/providers/__init__.py
miu_core/providers/anthropic.py
miu_core/providers/base.py
miu_core/providers/google.py
miu_core/providers/openai.py
miu_core/skills/__init__.py
miu_core/skills/base.py
miu_core/skills/loader.py
miu_core/skills/manifest.py
miu_core/skills/registry.py
miu_core/tools/__init__.py
miu_core/tools/base.py
miu_core/tools/registry.py
miu_core/tracing/__init__.py
miu_core/tracing/noop.py
miu_core/tracing/otel.py
miu_core/tracing/types.py
miu_core-1.0.0.dist-info/METADATA
miu_core-1.0.0.dist-info/WHEEL
miu_core-1.0.0.dist-info/RECORD
